jitb/__init__.py
jitb/cda.py
jitb/cdb.py
jitb/error.py
jitb/exitify.py
jitb/ntb.py
jitb/rb.py
jitb-0.1.1.dist-info/WHEEL
jitb-0.1.1.dist-info/METADATA
jitb-0.1.1.dist-info/RECORD
