Metadata-Version: 2.1
Name: jitb
Version: 0.1.1
Summary: A small library containing some utilities to jump-scare you
Home-page: https://github.com/xpodev/jitb-py
Author: Binyamin Y Cohen
Author-email: binyamincohen555@gmail.com
Requires-Python: >=3.9,<4.0
Classifier: Programming Language :: Python :: 3
Classifier: Programming Language :: Python :: 3.10
Classifier: Programming Language :: Python :: 3.9
Project-URL: Repository, https://github.com/xpodev/jitb-py
